auth_rsha/__init__.py
auth_rsha/cli.py
auth_rsha/config.py
auth_rsha/deps.py
auth_rsha/hashing.py
auth_rsha/jwt.py
auth_rsha/py.typed
auth_rsha/repo.py
auth_rsha/schemas.py
auth_rsha/routers/auth.py
auth_rsha-0.1.2.dist-info/METADATA
auth_rsha-0.1.2.dist-info/WHEEL
auth_rsha-0.1.2.dist-info/entry_points.txt
auth_rsha-0.1.2.dist-info/top_level.txt
auth_rsha-0.1.2.dist-info/RECORD
