Metadata-Version: 2.4
Name: auth-rsha
Version: 0.1.2
Summary: Reusable JWT auth for FastAPI (password flow)
Author-email: Hayk Sargsyan <hsargsyan889@gmail.com>
License: MIT
Project-URL: Homepage, https://github.com/sargsyanhayko/rsha_auth
Project-URL: Documentation, https://sargsyanhayko.github.io/rsha_auth/
Project-URL: Issues, https://github.com/sargsyanhayko/rsha_auth/issues
Project-URL: Source, https://github.com/sargsyanhayko/rsha_auth
Classifier: Programming Language :: Python :: 3
Classifier: Framework :: FastAPI
Classifier: License :: OSI Approved :: MIT License
Classifier: Typing :: Typed
Requires-Python: >=3.10
Requires-Dist: fastapi>=0.115
Requires-Dist: pydantic>=2.6
Requires-Dist: python-jose[cryptography]>=3.3.0
Requires-Dist: passlib>=1.7.4
Requires-Dist: argon2-cffi>=23.1.0
Requires-Dist: pydantic-settings>=2.4
